<?xml version="1.0" encoding="UTF-8"?>
<hdr:Document xmlns:hdr="http://www.exchangenetwork.net/schema/v1.0/ExchangeNetworkDocument.xsd" xmlns:ds="http://www.w3.org/2000/09/xmldsig#" xmlns:xsi="http://www.w3.org/2001/XMLSchema-instance" xsi:schemaLocation="http://www.exchangenetwork.net/schema/v1.0/ExchangeNetworkDocument.xsd http://www.exchangenetwork.net/schema/v1.0/ExchangeNetworkDocument.xsd" Id="ID123456">
	<hdr:Header>
		<hdr:Author>Dwane Young</hdr:Author>
		<hdr:Organization>US Environmental Protection Agency</hdr:Organization>
		<hdr:Title>Handler-Example-Submission</hdr:Title>
		<hdr:CreationTime>2009-12-11T17:37:58</hdr:CreationTime>
		<hdr:Comment>RCRA submission</hdr:Comment>
		<hdr:DataService>FinancialAssuranceSubmission</hdr:DataService>
		<hdr:ContactInfo>young.dwane@epa.gov</hdr:ContactInfo>
		<hdr:Notification>young.dwane@epa.gov</hdr:Notification>
		<hdr:Sensitivity>Unclassified</hdr:Sensitivity>
		<hdr:Property>
			<hdr:name>RCRAInfoUserID</hdr:name>
			<hdr:value>YDB</hdr:value>
		</hdr:Property>
		<hdr:Property>
			<hdr:name>RCRAInfoStateCode</hdr:name>
			<hdr:value>KS</hdr:value>
		</hdr:Property>
		<hdr:Property>
			<hdr:name>notificationURI</hdr:name>
			<hdr:value>young.dwane@epa.gov</hdr:value>
		</hdr:Property>
	</hdr:Header>
	<hdr:Payload Operation="RCRA-Transactional|FA">
<RC:FinancialAssuranceSubmission xmlns:RC="http://www.exchangenetwork.net/schema/RCRA/5" xmlns:xsi="http://www.w3.org/2001/XMLSchema-instance" xsi:schemaLocation="http://www.exchangenetwork.net/schema/RCRA/5 http://www.exchangenetwork.net/schema/RCRA/5/0/RCRA_FinancialAssuranceSubmission_v5.0_draft.xsd">
	<RC:FinancialAssuranceFacilitySubmission>
		<RC:HandlerID>KSR00054DEMO</RC:HandlerID>
		<RC:CostEstimate>
			<RC:TransactionCode>A</RC:TransactionCode>
			<RC:ActivityLocationCode>KS</RC:ActivityLocationCode>
			<RC:CostEstimateTypeCode>C</RC:CostEstimateTypeCode>
			<RC:CostEstimateAgencyCode>S</RC:CostEstimateAgencyCode>
			<RC:CostEstimateSequenceNumber>1</RC:CostEstimateSequenceNumber>
			<RC:ResponsiblePersonDataOwnerCode>KS</RC:ResponsiblePersonDataOwnerCode>
			<RC:ResponsiblePersonID>KSDAD</RC:ResponsiblePersonID>
			<RC:CostEstimateAmount>590000</RC:CostEstimateAmount>
			<RC:CostEstimateDate>2009-06-11</RC:CostEstimateDate>
			<RC:CostEstimateReasonCode>I</RC:CostEstimateReasonCode>
			<RC:AreaUnitNotesText>An example of Notes related to the Area</RC:AreaUnitNotesText>
			<RC:SupplementalInformationText>An example of comments.</RC:SupplementalInformationText>
			<RC:CostEstimateRelatedMechanism>
				<RC:TransactionCode>A</RC:TransactionCode>
				<RC:ActivityLocationCode>KS</RC:ActivityLocationCode>
				<RC:MechanismAgencyCode>S</RC:MechanismAgencyCode>
				<RC:MechanismSequenceNumber>1</RC:MechanismSequenceNumber>
				<RC:MechanismDetailSequenceNumber>1</RC:MechanismDetailSequenceNumber>
			</RC:CostEstimateRelatedMechanism>
		</RC:CostEstimate>
		<RC:CostEstimate>
			<RC:TransactionCode>A</RC:TransactionCode>
			<RC:ActivityLocationCode>KS</RC:ActivityLocationCode>
			<RC:CostEstimateTypeCode>S</RC:CostEstimateTypeCode>
			<RC:CostEstimateAgencyCode>S</RC:CostEstimateAgencyCode>
			<RC:CostEstimateSequenceNumber>2</RC:CostEstimateSequenceNumber>
			<RC:ResponsiblePersonDataOwnerCode>KS</RC:ResponsiblePersonDataOwnerCode>
			<RC:ResponsiblePersonID>KSDAD</RC:ResponsiblePersonID>
			<RC:CostEstimateAmount>2000000</RC:CostEstimateAmount>
			<RC:CostEstimateDate>2009-06-11</RC:CostEstimateDate>
			<RC:CostEstimateReasonCode>I</RC:CostEstimateReasonCode>
			<RC:CostEstimateRelatedMechanism>
				<RC:TransactionCode>A</RC:TransactionCode>
				<RC:ActivityLocationCode>KS</RC:ActivityLocationCode>
				<RC:MechanismAgencyCode>S</RC:MechanismAgencyCode>
				<RC:MechanismSequenceNumber>1</RC:MechanismSequenceNumber>
				<RC:MechanismDetailSequenceNumber>1</RC:MechanismDetailSequenceNumber>
			</RC:CostEstimateRelatedMechanism>
		</RC:CostEstimate>
		<RC:CostEstimate>
			<RC:TransactionCode>A</RC:TransactionCode>
			<RC:ActivityLocationCode>KS</RC:ActivityLocationCode>
			<RC:CostEstimateTypeCode>N</RC:CostEstimateTypeCode>
			<RC:CostEstimateAgencyCode>S</RC:CostEstimateAgencyCode>
			<RC:CostEstimateSequenceNumber>2</RC:CostEstimateSequenceNumber>
			<RC:ResponsiblePersonDataOwnerCode>KS</RC:ResponsiblePersonDataOwnerCode>
			<RC:ResponsiblePersonID>KSDAD</RC:ResponsiblePersonID>
			<RC:CostEstimateAmount>6000000</RC:CostEstimateAmount>
			<RC:CostEstimateDate>2009-06-11</RC:CostEstimateDate>
			<RC:CostEstimateReasonCode>I</RC:CostEstimateReasonCode>
			<RC:CostEstimateRelatedMechanism>
				<RC:TransactionCode>A</RC:TransactionCode>
				<RC:ActivityLocationCode>KS</RC:ActivityLocationCode>
				<RC:MechanismAgencyCode>S</RC:MechanismAgencyCode>
				<RC:MechanismSequenceNumber>1</RC:MechanismSequenceNumber>
				<RC:MechanismDetailSequenceNumber>1</RC:MechanismDetailSequenceNumber>
			</RC:CostEstimateRelatedMechanism>
		</RC:CostEstimate>
		<RC:Mechanism>
			<RC:TransactionCode>A</RC:TransactionCode>
			<RC:ActivityLocationCode>KS</RC:ActivityLocationCode>
			<RC:MechanismAgencyCode>S</RC:MechanismAgencyCode>
			<RC:MechanismSequenceNumber>1</RC:MechanismSequenceNumber>
			<RC:MechanismTypeDataOwnerCode>HQ</RC:MechanismTypeDataOwnerCode>
			<RC:MechanismTypeCode>I</RC:MechanismTypeCode>
			<RC:ProviderText>The Grande Insurance Company</RC:ProviderText>
			<RC:ProviderFullContactName>Jim Jones</RC:ProviderFullContactName>
			<RC:TelephoneNumberText>8015552222</RC:TelephoneNumberText>
			<RC:MechanismDetail>
				<RC:TransactionCode>A</RC:TransactionCode>
				<RC:MechanismDetailSequenceNumber>1</RC:MechanismDetailSequenceNumber>
				<RC:MechanismIdentificationText>993444513432221</RC:MechanismIdentificationText>
				<RC:FaceValueAmount>10000000</RC:FaceValueAmount>
				<RC:EffectiveDate>2009-06-11</RC:EffectiveDate>
				<RC:ExpirationDate>2013-06-30</RC:ExpirationDate>
			</RC:MechanismDetail>
		</RC:Mechanism>
	</RC:FinancialAssuranceFacilitySubmission>
</RC:FinancialAssuranceSubmission>
</hdr:Payload>
</hdr:Document>

